test_active_state_recipes/.__init__.py.un~
test_active_state_recipes/__init__.py
test_active_state_recipes-0.0.1.dist-info/WHEEL
test_active_state_recipes-0.0.1.dist-info/METADATA
test_active_state_recipes-0.0.1.dist-info/RECORD
