Metadata-Version: 1.2
Name: test_active_state_recipes
Version: 0.0.1
Summary: ActiveState Code Recipes magics
Home-page: https://github.com/Carreau/test_active_state_recipes
License: UNKNOWN
Author: Matthias Bussonnier
Author-email: bussonniermatthias@gmail.com
Classifier: License :: OSI Approved :: MIT License
